objz/caching.py
objz/methods.py
objz/objects.py
objz/serials.py
objz-101.dist-info/METADATA
objz-101.dist-info/WHEEL
objz-101.dist-info/top_level.txt
objz-101.dist-info/RECORD
