Metadata-Version: 2.4
Name: objz
Version: 101
Summary: objects
Author-email: Bart Thate <bthate@dds.nl>
License-Expression: Unlicense
Project-URL: home, https://pypi.org/project/objz
Project-URL: bugs, https://github.com/botlibX/objz/issues
Project-URL: source, https://github.com/botlibX/objz
Classifier: Development Status :: 3 - Alpha
Classifier: Operating System :: Unix
Classifier: Programming Language :: Python :: 3
Classifier: Topic :: Utilities
